CHANGES.rst
LICENSE.txt
MANIFEST.in
README.rst
setup.py
django_mcmo.egg-info/PKG-INFO
django_mcmo.egg-info/SOURCES.txt
django_mcmo.egg-info/dependency_links.txt
django_mcmo.egg-info/not-zip-safe
django_mcmo.egg-info/requires.txt
django_mcmo.egg-info/top_level.txt
mcmo/__init__.py
mcmo/management.py
mcmo/version.py