Metadata-Version: 1.1
Name: django-mcmo
Version: 2.1.2
Summary: Allows multiple apps to override the same management command in Django
Home-page: https://bitbucket.org/tkhyn/django-mcmo
Author: Thomas Khyn
Author-email: thomas@ksytek.com
License: UNKNOWN
Keywords: django,management,multiple
Platform: UNKNOWN
Classifier: Programming Language :: Python
Classifier: Programming Language :: Python :: 2.6
Classifier: Programming Language :: Python :: 2.7
Classifier: Programming Language :: Python :: 3.3
Classifier: Programming Language :: Python :: 3.4
Classifier: License :: OSI Approved :: MIT License
Classifier: Operating System :: OS Independent
Classifier: Development Status :: 5 - Production/Stable
Classifier: Intended Audience :: Developers
Classifier: Framework :: Django
Classifier: Environment :: Other Environment
Classifier: Topic :: Software Development :: Libraries
Classifier: Topic :: Utilities
